armada_client/__init__.py
armada_client/_proto_methods.py
armada_client/asyncio_client.py
armada_client/client.py
armada_client/event.py
armada_client/iterators.py
armada_client/log_client.py
armada_client/permissions.py
armada_client/py.typed
armada_client/typings.py
armada_client/armada/binoculars_pb2.py
armada_client/armada/binoculars_pb2.pyi
armada_client/armada/binoculars_pb2_grpc.py
armada_client/armada/event_pb2.py
armada_client/armada/event_pb2.pyi
armada_client/armada/event_pb2_grpc.py
armada_client/armada/health_pb2.py
armada_client/armada/health_pb2.pyi
armada_client/armada/health_pb2_grpc.py
armada_client/armada/job_pb2.py
armada_client/armada/job_pb2.pyi
armada_client/armada/job_pb2_grpc.py
armada_client/armada/submit_pb2.py
armada_client/armada/submit_pb2.pyi
armada_client/armada/submit_pb2_grpc.py
armada_client/gen/event_typings.py
armada_client/github/com/gogo/protobuf/gogoproto/gogo_pb2.py
armada_client/github/com/gogo/protobuf/gogoproto/gogo_pb2.pyi
armada_client/google/api/annotations_pb2.py
armada_client/google/api/annotations_pb2.pyi
armada_client/google/api/annotations_pb2_grpc.py
armada_client/google/api/http_pb2.py
armada_client/google/api/http_pb2.pyi
armada_client/google/api/http_pb2_grpc.py
armada_client/internal/__init__.py
armada_client/internal/binoculars_client.py
armada_client/k8s/io/api/core/v1/generated_pb2.py
armada_client/k8s/io/api/core/v1/generated_pb2.pyi
armada_client/k8s/io/api/networking/v1/generated_pb2.py
armada_client/k8s/io/api/networking/v1/generated_pb2.pyi
armada_client/k8s/io/apimachinery/pkg/api/resource/generated_pb2.py
armada_client/k8s/io/apimachinery/pkg/api/resource/generated_pb2.pyi
armada_client/k8s/io/apimachinery/pkg/apis/meta/v1/generated_pb2.py
armada_client/k8s/io/apimachinery/pkg/apis/meta/v1/generated_pb2.pyi
armada_client/k8s/io/apimachinery/pkg/runtime/generated_pb2.py
armada_client/k8s/io/apimachinery/pkg/runtime/generated_pb2.pyi
armada_client-0.4.13.dist-info/METADATA
armada_client-0.4.13.dist-info/WHEEL
armada_client-0.4.13.dist-info/top_level.txt
armada_client-0.4.13.dist-info/RECORD
