Metadata-Version: 2.4
Name: armada_client
Version: 0.4.13
Summary: Armada gRPC API python client
Author-email: G-Research Open Source Software <armada@armadaproject.io>
License: Apache Software License
Requires-Python: >=3.9
Requires-Dist: grpcio==1.68.1
Requires-Dist: grpcio-tools==1.68.1
Requires-Dist: mypy-protobuf>=3.6.0
Requires-Dist: protobuf>=5.28.1
Provides-Extra: format
Requires-Dist: black>=23.7.0; extra == "format"
Requires-Dist: flake8>=7.0.0; extra == "format"
Requires-Dist: pylint>=2.17.5; extra == "format"
Provides-Extra: docs
Requires-Dist: sphinx==7.1.2; extra == "docs"
Requires-Dist: sphinx-jekyll-builder==0.3.0; extra == "docs"
Requires-Dist: sphinx-toolbox==3.2.0b1; extra == "docs"
Requires-Dist: sphinx-markdown-builder==0.5.5; extra == "docs"
Provides-Extra: test
Requires-Dist: pytest==7.3.1; extra == "test"
Requires-Dist: coverage==6.5.0; extra == "test"
Requires-Dist: pytest-asyncio==0.21.1; extra == "test"
